[{"contractYm":"202604","contractDay":"25","price":105000,"priceEok":"10억5,000","deposit":0,"monthlyRent":0,"reqGb":"","rnuYn":"","area":79.8807,"areaPyeong":32.065,"floor":12,"dealType":" "},{"contractYm":"202604","contractDay":"12","price":128000,"priceEok":"12억8,000","deposit":0,"monthlyRent":0,"reqGb":"","rnuYn":"","area":101.6281,"areaPyeong":41.14,"floor":22,"dealType":" "},{"contractYm":"202604","contractDay":"08","price":59000,"priceEok":"5억9,000","deposit":59000,"monthlyRent":0,"reqGb":"신규","rnuYn":"-","area":101.6281,"areaPyeong":41.14,"floor":28,"dealType":"전세"},{"contractYm":"202603","contractDay":"31","price":0,"priceEok":"5억4,000","deposit":54000,"monthlyRent":0,"reqGb":"","rnuYn":"","area":79.8807,"areaPyeong":32.065,"floor":30,"dealType":"전세"},{"contractYm":"202603","contractDay":"31","price":0,"priceEok":"5억9,000","deposit":59000,"monthlyRent":0,"reqGb":"","rnuYn":"","area":101.6281,"areaPyeong":41.14,"floor":25,"dealType":"전세"},{"contractYm":"202603","contractDay":"19","price":0,"priceEok":"5억5,000","deposit":55000,"monthlyRent":0,"reqGb":"","rnuYn":"","area":79.8807,"areaPyeong":32.065,"floor":34,"dealType":"전세"},{"contractYm":"202603","contractDay":"06","price":109800,"priceEok":"10억9,800","deposit":0,"monthlyRent":0,"reqGb":"","rnuYn":"","area":79.8807,"areaPyeong":32.065,"floor":30,"dealType":"중개거래"},{"contractYm":"202602","contractDay":"23","price":107000,"priceEok":"10억7,000","deposit":0,"monthlyRent":0,"reqGb":"","rnuYn":"","area":78.059,"areaPyeong":31.46,"floor":18,"dealType":"중개거래"},{"contractYm":"202602","contractDay":"14","price":102000,"priceEok":"10억2,000","deposit":0,"monthlyRent":0,"reqGb":"","rnuYn":"","area":78.059,"areaPyeong":31.46,"floor":7,"dealType":"중개거래"},{"contractYm":"202602","contractDay":"12","price":106500,"priceEok":"10억6,500","deposit":0,"monthlyRent":0,"reqGb":"","rnuYn":"","area":78.059,"areaPyeong":31.46,"floor":34,"dealType":"중개거래"},{"contractYm":"202602","contractDay":"09","price":107000,"priceEok":"10억7,000","deposit":0,"monthlyRent":0,"reqGb":"","rnuYn":"","area":79.8807,"areaPyeong":32.065,"floor":34,"dealType":"중개거래"},{"contractYm":"202602","contractDay":"07","price":104800,"priceEok":"10억4,800","deposit":0,"monthlyRent":0,"reqGb":"","rnuYn":"","area":79.8807,"areaPyeong":32.065,"floor":8,"dealType":"중개거래"},{"contractYm":"202601","contractDay":"31","price":102500,"priceEok":"10억2,500","deposit":0,"monthlyRent":0,"reqGb":"","rnuYn":"","area":79.8807,"areaPyeong":32.065,"floor":14,"dealType":"중개거래"},{"contractYm":"202601","contractDay":"30","price":103000,"priceEok":"10억3,000","deposit":0,"monthlyRent":0,"reqGb":"","rnuYn":"","area":78.059,"areaPyeong":31.46,"floor":32,"dealType":"중개거래"},{"contractYm":"202601","contractDay":"26","price":99000,"priceEok":"9억9,000","deposit":0,"monthlyRent":0,"reqGb":"","rnuYn":"","area":78.059,"areaPyeong":31.46,"floor":17,"dealType":"중개거래"}]