[{"contractYm":"202605","contractDay":"20","price":157000,"priceEok":"15억7,000","deposit":0,"monthlyRent":0,"reqGb":"","rnuYn":"","area":96.5843,"areaPyeong":39.324999999999996,"floor":34,"dealType":" "},{"contractYm":"202605","contractDay":"18","price":114500,"priceEok":"11억4,500","deposit":0,"monthlyRent":0,"reqGb":"","rnuYn":"","area":84.4985,"areaPyeong":34.485,"floor":12,"dealType":" "},{"contractYm":"202605","contractDay":"11","price":44100,"priceEok":"4억4,100","deposit":44100,"monthlyRent":0,"reqGb":"갱신","rnuYn":"사용","area":84.4985,"areaPyeong":34.485,"floor":12,"dealType":"전세"},{"contractYm":"202605","contractDay":"07","price":65000,"priceEok":"6억5,000","deposit":65000,"monthlyRent":0,"reqGb":"신규","rnuYn":" ","area":84.6065,"areaPyeong":34.485,"floor":33,"dealType":"전세"},{"contractYm":"202605","contractDay":"06","price":42000,"priceEok":"4억2,000","deposit":42000,"monthlyRent":0,"reqGb":"갱신","rnuYn":"사용","area":71.6544,"areaPyeong":29.947499999999998,"floor":29,"dealType":"전세"},{"contractYm":"202604","contractDay":"29","price":63000,"priceEok":"6억3,000","deposit":63000,"monthlyRent":0,"reqGb":"신규","rnuYn":" ","area":84.6065,"areaPyeong":34.485,"floor":41,"dealType":"전세"},{"contractYm":"202604","contractDay":"26","price":154500,"priceEok":"15억4,500","deposit":0,"monthlyRent":0,"reqGb":"","rnuYn":"","area":96.5843,"areaPyeong":39.324999999999996,"floor":15,"dealType":" "},{"contractYm":"202604","contractDay":"25","price":119500,"priceEok":"11억9,500","deposit":0,"monthlyRent":0,"reqGb":"","rnuYn":"","area":84.4985,"areaPyeong":34.485,"floor":29,"dealType":" "},{"contractYm":"202604","contractDay":"20","price":30000,"priceEok":"3억 / 70만","deposit":30000,"monthlyRent":70,"reqGb":"갱신","rnuYn":" ","area":84.6065,"areaPyeong":34.485,"floor":28,"dealType":"월세"},{"contractYm":"202604","contractDay":"17","price":30000,"priceEok":"3억 / 130만","deposit":30000,"monthlyRent":130,"reqGb":"신규","rnuYn":" ","area":84.4985,"areaPyeong":34.485,"floor":41,"dealType":"월세"},{"contractYm":"202604","contractDay":"15","price":30000,"priceEok":"3억 / 70만","deposit":30000,"monthlyRent":70,"reqGb":"갱신","rnuYn":" ","area":84.6065,"areaPyeong":34.485,"floor":28,"dealType":"월세"},{"contractYm":"202604","contractDay":"07","price":157000,"priceEok":"15억7,000","deposit":0,"monthlyRent":0,"reqGb":"","rnuYn":"","area":96.5843,"areaPyeong":39.324999999999996,"floor":42,"dealType":" "},{"contractYm":"202604","contractDay":"04","price":134500,"priceEok":"13억4,500","deposit":0,"monthlyRent":0,"reqGb":"","rnuYn":"","area":84.6065,"areaPyeong":34.485,"floor":42,"dealType":" "},{"contractYm":"202604","contractDay":"04","price":116500,"priceEok":"11억6,500","deposit":0,"monthlyRent":0,"reqGb":"","rnuYn":"","area":84.4985,"areaPyeong":34.485,"floor":9,"dealType":" "},{"contractYm":"202604","contractDay":"04","price":70000,"priceEok":"7억","deposit":70000,"monthlyRent":0,"reqGb":"신규","rnuYn":" ","area":96.5843,"areaPyeong":39.324999999999996,"floor":41,"dealType":"전세"}]