[{"contractYm":"202604","contractDay":"02","price":29800,"priceEok":"2억9,800","deposit":0,"monthlyRent":0,"reqGb":"","rnuYn":"","area":84.9352,"areaPyeong":34.17155433999999,"floor":13,"dealType":"매매"},{"contractYm":"202604","contractDay":"02","price":28000,"priceEok":"2억8,000","deposit":0,"monthlyRent":0,"reqGb":"","rnuYn":"","area":84.9352,"areaPyeong":34.17155433999999,"floor":10,"dealType":"매매"},{"contractYm":"202604","contractDay":"01","price":28900,"priceEok":"2억8,900","deposit":0,"monthlyRent":0,"reqGb":"","rnuYn":"","area":84.9352,"areaPyeong":34.17155433999999,"floor":4,"dealType":"매매"}]